myoktros/__init__.py
myoktros/client.py
myoktros/command.py
myoktros/gesture.py
myoktros/robot.py
myoktros-0.3.0.dist-info/LICENSE
myoktros-0.3.0.dist-info/METADATA
myoktros-0.3.0.dist-info/WHEEL
myoktros-0.3.0.dist-info/entry_points.txt
myoktros-0.3.0.dist-info/RECORD
