Metadata-Version: 2.1
Name: myoktros
Version: 0.3.0
Summary: Myo EMG-based KT system for ROS
License: MIT
Author: Iori Mizutani
Author-email: iomz@sazanka.io
Requires-Python: >=3.10,<3.12
Classifier: License :: OSI Approved :: MIT License
Classifier: Programming Language :: Python :: 3
Classifier: Programming Language :: Python :: 3.10
Classifier: Programming Language :: Python :: 3.11
Requires-Dist: dl-myo (>=1.0.3)
Requires-Dist: joblib (>=1.2.0,<2.0.0)
Requires-Dist: numpy (>=1.24.3,<2.0.0)
Requires-Dist: pandas (>=2.0.2,<3.0.0)
Requires-Dist: scikit-learn (>=1.2.2,<2.0.0)
Requires-Dist: tensorflow (>=2.13.0rc1)
Requires-Dist: transitions (>=0.9.0,<0.10.0)
Requires-Dist: websockets (>=11.0.3,<12.0.0)
